README.md
setup.py
qttk/__init__.py
qttk/bollinger.py
qttk/chaikin_money_flow.py
qttk/cma.py
qttk/cumulative_sum.py
qttk/ema.py
qttk/indicators.py
qttk/lin_reg.py
qttk/ma.py
qttk/macd.py
qttk/opportunity_eval.py
qttk/pl_return.py
qttk/portfolio.py
qttk/profiler.py
qttk/profiler_v2.py
qttk/r_squared.py
qttk/rsi.py
qttk/sharpe.py
qttk/version.txt
qttk/wma.py
qttk.egg-info/PKG-INFO
qttk.egg-info/SOURCES.txt
qttk.egg-info/dependency_links.txt
qttk.egg-info/requires.txt
qttk.egg-info/top_level.txt
qttk/data/alternative_data/AWU.csv
qttk/data/alternative_data/HECP.csv
qttk/data/alternative_data/HRVC.csv
qttk/data/alternative_data/HXX.csv
qttk/data/alternative_data/NSLG.csv
qttk/data/alternative_data/PQCE.csv
qttk/data/alternative_data/RZW.csv
qttk/data/alternative_data/TRE.csv
qttk/data/alternative_data/WFS.csv
qttk/data/alternative_data/ZGL.csv
qttk/data/eod/AWU.csv
qttk/data/eod/HECP.csv
qttk/data/eod/HRVC.csv
qttk/data/eod/HXX.csv
qttk/data/eod/NSLG.csv
qttk/data/eod/PQCE.csv
qttk/data/eod/RZW.csv
qttk/data/eod/TRE.csv
qttk/data/eod/WFS.csv
qttk/data/eod/ZGL.csv
qttk/data/validation_data/SPY_validation.xlsx
qttk/data/validation_data/Validation-data_input.csv
qttk/data/validation_data/cma_validation_data.csv
qttk/data/validation_data/down.csv
qttk/data/validation_data/down_avg.csv
qttk/data/validation_data/ema_validation_data.csv
qttk/data/validation_data/portfolio_sharpe_validation.xlsx
qttk/data/validation_data/sma_validation_data.csv
qttk/data/validation_data/test_rets.csv
qttk/data/validation_data/up.csv
qttk/data/validation_data/up_avg.csv
qttk/data/validation_data/wma_validation_data.csv
qttk/examples/bollinger.py
qttk/examples/log_vs_pct_return.py
qttk/examples/ma_crossover.py
qttk/examples/portfolio_example.py
qttk/examples/price_crossover.py
qttk/examples/simple_plot.py
qttk/utils/__init__.py
qttk/utils/data_utils.py
qttk/utils/data_validation.py
qttk/utils/qttk_plot.py
qttk/utils/sample_data.py