Metadata-Version: 2.1
Name: qttk
Version: 0.1.3
Summary: Quantitative Trading Toolkit
Home-page: https://github.com/conlan-scientific/qttk
Author: Conlan Scientific Open-source Development Cohort
Author-email: chris@conlan.io
License: GNU General Public License v3.0
Platform: UNKNOWN
Classifier: Intended Audience :: Developers
Classifier: Intended Audience :: Financial and Insurance Industry
Classifier: License :: OSI Approved :: GNU General Public License v3 (GPLv3)
Classifier: Operating System :: POSIX :: Linux
Classifier: Operating System :: Microsoft :: Windows
Classifier: Operating System :: MacOS :: MacOS X
Classifier: Programming Language :: Python :: 3
Classifier: Programming Language :: Python :: 3.6
Classifier: Programming Language :: Python :: 3.7
Classifier: Programming Language :: Python :: 3.8
Classifier: Programming Language :: Python :: 3.9
